{
  "last_node_id": 107,
  "last_link_id": 133,
  "nodes": [
    {
      "id": 104,
      "type": "ZenkaiPrompt",
      "pos": [
        -8268.69140625,
        3734.3095703125
      ],
      "size": [
        315,
        106
      ],
      "flags": {},
      "order": 0,
      "mode": 0,
      "inputs": [],
      "outputs": [
        {
          "name": "STRING",
          "type": "STRING",
          "links": [
            132
          ],
          "slot_index": 0
        }
      ],
      "properties": {
        "Node name for S&R": "ZenkaiPrompt"
      },
      "widgets_values": [
        "01-trad-ahab.txt",
        1570669969,
        "randomize"
      ]
    },
    {
      "id": 105,
      "type": "ShowText|pysssss",
      "pos": [
        -7829.23486328125,
        3735.59765625
      ],
      "size": [
        352.76141357421875,
        144.7451171875
      ],
      "flags": {},
      "order": 3,
      "mode": 0,
      "inputs": [
        {
          "name": "text",
          "type": "STRING",
          "link": 132,
          "widget": {
            "name": "text"
          }
        }
      ],
      "outputs": [
        {
          "name": "STRING",
          "type": "STRING",
          "links": null,
          "shape": 6
        }
      ],
      "properties": {
        "Node name for S&R": "ShowText|pysssss"
      },
      "widgets_values": [
        "",
        "An old whaler sits alone in his cabin, studying a massive tooth from a sperm whale. He has a gray beard and weather-worn face; his wooden leg rests against a sea chest. The camera slowly tracks backward. The cabin is filled with whale bones and ancient hunting tools. The scene appears to be from a TV show."
      ]
    },
    {
      "id": 106,
      "type": "Note",
      "pos": [
        -8257.0927734375,
        3896.688720703125
      ],
      "size": [
        292.3469543457031,
        113.42367553710938
      ],
      "flags": {},
      "order": 1,
      "mode": 0,
      "inputs": [],
      "outputs": [],
      "properties": {},
      "widgets_values": [
        "Zenkai Prompt is a prompt list loader, feed it into your clip text encoder, the seed controls which line is loaded.\n\n/prompts/ contains the text files\n\nnew line = new prompt"
      ],
      "color": "#432",
      "bgcolor": "#653"
    },
    {
      "id": 1,
      "type": "Note",
      "pos": [
        -8628.9736328125,
        3730.3603515625
      ],
      "size": [
        320.7658996582031,
        262.17633056640625
      ],
      "flags": {},
      "order": 2,
      "mode": 0,
      "inputs": [],
      "outputs": [],
      "properties": {},
      "widgets_values": [
        "DJZ-Nodes-Examples-Zenkai-Prompt\n\n# Video: \nhttps://www.youtube.com/@FiveBelowFiveUK\n# Workflow: https://civitai.com/user/driftjohnson/models\n# Website:\nhttps://www.fivebelowfive.uk\n\n\n\n[discord early editions]\nhttps://discord.com/invite/uubQXhwzkj \n"
      ],
      "color": "#432",
      "bgcolor": "#653"
    }
  ],
  "links": [
    [
      132,
      104,
      0,
      105,
      0,
      "STRING"
    ]
  ],
  "groups": [],
  "config": {},
  "extra": {
    "ds": {
      "scale": 0.9389095771738513,
      "offset": [
        8802.830515062113,
        -3544.3892987617173
      ]
    },
    "VHS_latentpreview": false,
    "VHS_latentpreviewrate": 0
  },
  "version": 0.4
}